{
  "unversionedId": "quickstart",
  "id": "quickstart",
  "title": "",
  "description": "",
  "source": "@site/docs/quickstart.md",
  "sourceDirName": ".",
  "slug": "/quickstart",
  "permalink": "/quickstart",
  "draft": false,
  "tags": [],
  "version": "current",
  "frontMatter": {
    "sidebar_label": "Quickstart",
    "title": ""
  },
  "sidebar": "elemental",
  "previous": {
    "title": "Overview",
    "permalink": "/"
  },
  "next": {
    "title": "Architecture",
    "permalink": "/architecture"
  }
}